<system>
	<name>HD 148156</name>
	<rightascension>16 28 17</rightascension>
	<declination>-46 19 03</declination>
	<distance errorminus="3.07" errorplus="2.75">53.05</distance>
	<star>
		<name>HD 148156</name>
		<mass>1.22</mass>
		<radius errorminus="0.03" errorplus="0.03">1.21</radius>
		<magV errorminus="0.011" errorplus="0.011">7.689</magV>
		<magB errorminus="0.016" errorplus="0.016">8.257</magB>
		<magJ errorminus="0.018" errorplus="0.018">6.688</magJ>
		<magH errorminus="0.024" errorplus="0.024">6.489</magH>
		<magK errorminus="0.022" errorplus="0.022">6.397</magK>
		<temperature errorminus="28.00" errorplus="28.00">6308.00</temperature>
		<metallicity errorminus="0.020" errorplus="0.020">0.290</metallicity>
		<spectraltype>G0/2 V</spectraltype>
		<planet>
			<name>HD 148156 b</name>
			<list>Confirmed planets</list>
			<mass errorminus="0.05000" errorplus="0.67000" type="Msini">0.85000</mass>
			<period errorminus="28.00000000" errorplus="28.00000000">1027.00000000</period>
			<semimajoraxis errorminus="0.050000" errorplus="0.040000">2.450000</semimajoraxis>
			<eccentricity errorminus="0.090000" errorplus="0.040000">0.520000</eccentricity>
			<periastron errorminus="12.0000" errorplus="17.0000">35.0000</periastron>
			<periastrontime errorminus="20.000000" errorplus="20.000000">2454707.000000</periastrontime>
			<maximumrvtime errorminus="20.000000" errorplus="20.000000">2454707.000000</maximumrvtime>
			<temperature>191.9</temperature>
			<discoverymethod>RV</discoverymethod>
			<lastupdate>16/12/02</lastupdate>
			<discoveryyear>2009</discoveryyear>
		</planet>
	</star>
</system>
