<system>
	<name>Kepler-293</name>
	<name>KOI-1366</name>
	<name>KIC 6932987</name>
	<rightascension>19 05 25</rightascension>
	<declination>+42 24 23</declination>
	<distance>1289.47</distance>
	<star>
		<name>Kepler-293</name>
		<name>KOI-1366</name>
		<name>KIC 6932987</name>
		<mass errorminus="0.0630" errorplus="0.0630">1.01</mass>
		<radius errorminus="0.40" errorplus="0.40">0.96</radius>
		<magV>15.368</magV>
		<magJ errorminus="0.023" errorplus="0.023">14.098</magJ>
		<magH errorminus="0.029" errorplus="0.029">13.781</magH>
		<magK errorminus="0.043" errorplus="0.043">13.661</magK>
		<temperature errorminus="200.00" errorplus="200.00">5804.00</temperature>
		<metallicity>0.134</metallicity>
		<planet>
			<name>Kepler-293 b</name>
			<name>KOI-1366 b</name>
			<name>KOI-1366.01</name>
			<name>KIC 6932987 b</name>
			<name>KIC 6932987.01</name>
			<list>Confirmed planets</list>
			<radius errorminus="0.116" errorplus="0.116">0.274</radius>
			<period errorminus="0.00007900" errorplus="0.00007900">19.25419600</period>
			<semimajoraxis>0.144000</semimajoraxis>
			<description>Kepler-293 b has been discovered by the Kepler spacecraft and was originally classified as a planet candidate. A new statistical analysis led by a team at NASA Ames Research Center has validated the planet with more than 99 percent confidence. Although many parameters of Kepler-293 b are still unknown, the object is highly unlikely to be a false positive.</description>
			<discoverymethod>transit</discoverymethod>
			<transittime errorminus=".002450" errorplus="0.002450" unit="BJD">2454997.781330</transittime>
			<istransiting>1</istransiting>
			<lastupdate>16/12/02</lastupdate>
			<discoveryyear>2014</discoveryyear>
		</planet>
		<planet>
			<name>Kepler-293 c</name>
			<name>KOI-1366 c</name>
			<name>KOI-1366.02</name>
			<name>KIC 6932987 c</name>
			<name>KIC 6932987.02</name>
			<list>Confirmed planets</list>
			<radius errorminus="0.145" errorplus="0.145">0.342</radius>
			<period errorminus="0.00046600" errorplus="0.00046600">54.15574300</period>
			<semimajoraxis>0.286000</semimajoraxis>
			<description>Kepler-293 c has been discovered by the Kepler spacecraft and was originally classified as a planet candidate. A new statistical analysis led by a team at NASA Ames Research Center has validated the planet with more than 99 percent confidence. Although many parameters of Kepler-293 c are still unknown, the object is highly unlikely to be a false positive.</description>
			<discoverymethod>transit</discoverymethod>
			<transittime errorminus=".005210" errorplus="0.005210" unit="BJD">2455005.365150</transittime>
			<istransiting>1</istransiting>
			<lastupdate>16/12/02</lastupdate>
			<discoveryyear>2014</discoveryyear>
		</planet>
	</star>
</system>
