<system>
	<name>Kepler-265</name>
	<name>KOI-1052</name>
	<name>KIC 5956342</name>
	<rightascension>19 22 02</rightascension>
	<declination>+41 14 41</declination>
	<distance>1511.13</distance>
	<star>
		<name>Kepler-265</name>
		<name>KOI-1052</name>
		<name>KIC 5956342</name>
		<mass errorminus="0.1100" errorplus="0.1100">1.03</mass>
		<radius errorminus="0.23" errorplus="0.23">1.10</radius>
		<magV>15.381</magV>
		<magJ errorminus="0.028" errorplus="0.028">14.252</magJ>
		<magH errorminus="0.034" errorplus="0.034">13.935</magH>
		<magK errorminus="0.051" errorplus="0.051">13.897</magK>
		<temperature errorminus="118.00" errorplus="118.00">5835.00</temperature>
		<metallicity>-0.311</metallicity>
		<planet>
			<name>Kepler-265 c</name>
			<name>KOI-1052 c</name>
			<name>KOI-1052.01</name>
			<name>KIC 5956342 c</name>
			<name>KIC 5956342.01</name>
			<list>Confirmed planets</list>
			<radius errorminus="0.049" errorplus="0.049">0.235</radius>
			<period errorminus="0.00013600" errorplus="0.00013600">17.02893700</period>
			<semimajoraxis>0.127000</semimajoraxis>
			<description>Kepler-265 c has been discovered by the Kepler spacecraft and was originally classified as a planet candidate. A new statistical analysis led by a team at NASA Ames Research Center has validated the planet with more than 99 percent confidence. Although many parameters of Kepler-265 c are still unknown, the object is highly unlikely to be a false positive.</description>
			<discoverymethod>transit</discoverymethod>
			<transittime errorminus=".004790" errorplus="0.004790" unit="BJD">2454976.336420</transittime>
			<istransiting>1</istransiting>
			<lastupdate>16/12/02</lastupdate>
			<discoveryyear>2014</discoveryyear>
		</planet>
		<planet>
			<name>Kepler-265 b</name>
			<name>KOI-1052 b</name>
			<name>KOI-1052.02</name>
			<name>KIC 5956342 b</name>
			<name>KIC 5956342.02</name>
			<list>Confirmed planets</list>
			<radius errorminus="0.040" errorplus="0.040">0.166</radius>
			<period errorminus="0.00006300" errorplus="0.00006300">6.84626200</period>
			<semimajoraxis>0.069000</semimajoraxis>
			<description>Kepler-265 b has been discovered by the Kepler spacecraft and was originally classified as a planet candidate. A new statistical analysis led by a team at NASA Ames Research Center has validated the planet with more than 99 percent confidence. Although many parameters of Kepler-265 b are still unknown, the object is highly unlikely to be a false positive.</description>
			<discoverymethod>transit</discoverymethod>
			<transittime errorminus=".005640" errorplus="0.005640" unit="BJD">2454965.170370</transittime>
			<istransiting>1</istransiting>
			<lastupdate>16/12/02</lastupdate>
			<discoveryyear>2014</discoveryyear>
		</planet>
		<planet>
			<name>Kepler-265 e</name>
			<name>KOI-1052 e</name>
			<name>KOI-1052.03</name>
			<name>KIC 5956342 e</name>
			<name>KIC 5956342.03</name>
			<list>Confirmed planets</list>
			<radius errorminus="0.049" errorplus="0.049">0.231</radius>
			<period errorminus="0.00139600" errorplus="0.00139600">67.83102400</period>
			<semimajoraxis>0.319000</semimajoraxis>
			<description>Kepler-265 e has been discovered by the Kepler spacecraft and was originally classified as a planet candidate. A new statistical analysis led by a team at NASA Ames Research Center has validated the planet with more than 99 percent confidence. Although many parameters of Kepler-265 e are still unknown, the object is highly unlikely to be a false positive.</description>
			<discoverymethod>transit</discoverymethod>
			<transittime errorminus=".013350" errorplus="0.013350" unit="BJD">2454958.896950</transittime>
			<istransiting>1</istransiting>
			<lastupdate>16/12/02</lastupdate>
			<discoveryyear>2014</discoveryyear>
		</planet>
		<planet>
			<name>Kepler-265 d</name>
			<name>KOI-1052 d</name>
			<name>KOI-1052.04</name>
			<name>KIC 5956342 d</name>
			<name>KIC 5956342.04</name>
			<list>Confirmed planets</list>
			<radius errorminus="0.048" errorplus="0.048">0.222</radius>
			<period errorminus="0.00065800" errorplus="0.00065800">43.13061700</period>
			<semimajoraxis>0.236000</semimajoraxis>
			<description>Kepler-265 d has been discovered by the Kepler spacecraft and was originally classified as a planet candidate. A new statistical analysis led by a team at NASA Ames Research Center has validated the planet with more than 99 percent confidence. Although many parameters of Kepler-265 d are still unknown, the object is highly unlikely to be a false positive.</description>
			<discoverymethod>transit</discoverymethod>
			<transittime errorminus=".009800" errorplus="0.009800" unit="BJD">2454999.275370</transittime>
			<istransiting>1</istransiting>
			<lastupdate>16/12/02</lastupdate>
			<discoveryyear>2014</discoveryyear>
		</planet>
	</star>
</system>
