<system>
	<name>WASP-97</name>
	<rightascension>01 38 25</rightascension>
	<declination>-55 46 19</declination>
	<star>
		<name>WASP-97</name>
		<name>1SWASP J013825.04-554619.4</name>
		<name>2MASS 01382504-5546194</name>
		<mass errorminus="0.06" errorplus="0.06">1.12</mass>
		<radius errorminus="0.04" errorplus="0.04">1.06</radius>
		<magV>10.6</magV>
		<magB errorminus="0.06" errorplus="0.06">11.31</magB>
		<magJ errorminus="0.019" errorplus="0.019">9.407</magJ>
		<magH errorminus="0.020" errorplus="0.020">9.070</magH>
		<magK errorminus="0.028" errorplus="0.028">9.030</magK>
		<temperature errorminus="100.00" errorplus="100.00">5640.00</temperature>
		<age errorminus="8.300" errorplus="16.000">11.900</age>
		<metallicity errorminus="0.110" errorplus="0.110">0.230</metallicity>
		<spectraltype>G5</spectraltype>
		<planet>
			<name>WASP-97 b</name>
			<name>1SWASP J013825.04-554619.4 b</name>
			<name>2MASS 01382504-5546194 b</name>
			<list>Confirmed planets</list>
			<mass errorminus="0.05000" errorplus="0.05000" type="Mass">1.32000</mass>
			<radius errorminus="0.060" errorplus="0.060">1.130</radius>
			<period errorminus="0.00000100" errorplus="0.00000100">2.07276000</period>
			<semimajoraxis errorminus="0.000560" errorplus="0.000560">0.033030</semimajoraxis>
			<eccentricity>0.000000</eccentricity>
			<inclination errorminus="1.000" errorplus="1.300">88.000</inclination>
			<temperature errorminus="40" errorplus="40">1555</temperature>
			<description>This is a hot Jupiter discovered by the WASP team.</description>
			<discoverymethod>transit</discoverymethod>
			<transittime errorminus=".000180" errorplus="0.000180" unit="HJD-UTC">2456438.186830</transittime>
			<istransiting>1</istransiting>
			<lastupdate>16/12/02</lastupdate>
			<discoveryyear>2014</discoveryyear>
		</planet>
	</star>
</system>
